{"errors":[],"warnings":[],"namedChunkGroups":{"app":{"chunks":[6,0,2],"assets":["webpack-runtime-40ef2bd3d7bdf4f61b61.js","webpack-runtime-40ef2bd3d7bdf4f61b61.js.map","commons-45e5a1e2c5b521614814.js","commons-45e5a1e2c5b521614814.js.map","app-cc48ae6a90d503862cf9.js","app-cc48ae6a90d503862cf9.js.map"],"children":{},"childAssets":{}},"component---src-pages-404-js":{"chunks":[1,0,3],"assets":["styles.4975594821a6f2dd106b.css","styles-13461c9351b88a8e7a66.js","styles-13461c9351b88a8e7a66.js.map","commons-45e5a1e2c5b521614814.js","commons-45e5a1e2c5b521614814.js.map","component---src-pages-404-js-ff278732b74282ecb645.js","component---src-pages-404-js-ff278732b74282ecb645.js.map"],"children":{},"childAssets":{}},"component---src-pages-index-js":{"chunks":[1,0,4],"assets":["styles.4975594821a6f2dd106b.css","styles-13461c9351b88a8e7a66.js","styles-13461c9351b88a8e7a66.js.map","commons-45e5a1e2c5b521614814.js","commons-45e5a1e2c5b521614814.js.map","component---src-pages-index-js-ec0eba349bd136d35061.js","component---src-pages-index-js-ec0eba349bd136d35061.js.map"],"children":{},"childAssets":{}},"component---src-pages-page-2-js":{"chunks":[1,0,5],"assets":["styles.4975594821a6f2dd106b.css","styles-13461c9351b88a8e7a66.js","styles-13461c9351b88a8e7a66.js.map","commons-45e5a1e2c5b521614814.js","commons-45e5a1e2c5b521614814.js.map","component---src-pages-page-2-js-63f8d0677455d51246ff.js","component---src-pages-page-2-js-63f8d0677455d51246ff.js.map"],"children":{},"childAssets":{}}},"assetsByChunkName":{"app":["webpack-runtime-40ef2bd3d7bdf4f61b61.js","commons-45e5a1e2c5b521614814.js","app-cc48ae6a90d503862cf9.js"],"component---src-pages-404-js":["styles.4975594821a6f2dd106b.css","styles-13461c9351b88a8e7a66.js","commons-45e5a1e2c5b521614814.js","component---src-pages-404-js-ff278732b74282ecb645.js"],"component---src-pages-index-js":["styles.4975594821a6f2dd106b.css","styles-13461c9351b88a8e7a66.js","commons-45e5a1e2c5b521614814.js","component---src-pages-index-js-ec0eba349bd136d35061.js"],"component---src-pages-page-2-js":["styles.4975594821a6f2dd106b.css","styles-13461c9351b88a8e7a66.js","commons-45e5a1e2c5b521614814.js","component---src-pages-page-2-js-63f8d0677455d51246ff.js"]}}